c2cgeoportal/__init__.py
c2cgeoportal/forms.py
c2cgeoportal/models.py
c2cgeoportal/pyramid_.py
c2cgeoportal/resources.py
c2cgeoportal/stats.py
c2cgeoportal/subscribers.py
c2cgeoportal/version.py
c2cgeoportal/lib/__init__.py
c2cgeoportal/lib/authentication.py
c2cgeoportal/lib/bashcolor.py
c2cgeoportal/lib/cacheversion.py
c2cgeoportal/lib/caching.py
c2cgeoportal/lib/dbreflection.py
c2cgeoportal/lib/email_.py
c2cgeoportal/lib/filter_capabilities.py
c2cgeoportal/lib/functionality.py
c2cgeoportal/lib/lingua_extractor.py
c2cgeoportal/lib/print_.py
c2cgeoportal/lib/sqlalchemy_.py
c2cgeoportal/lib/wmstparsing.py
c2cgeoportal/lib/raster/__init__.py
c2cgeoportal/lib/raster/dbfutils.py
c2cgeoportal/lib/raster/georaster.py
c2cgeoportal/lib/raster/shputils.py
c2cgeoportal/locale/de/LC_MESSAGES/c2cgeoportal.mo
c2cgeoportal/locale/fr/LC_MESSAGES/c2cgeoportal.mo
c2cgeoportal/scaffolds/__init__.py
c2cgeoportal/scaffolds/__init__.pyc
c2cgeoportal/scaffolds/create/+dot+dockerignore_tmpl
c2cgeoportal/scaffolds/create/+dot+gitignore_tmpl
c2cgeoportal/scaffolds/create/+dot+travis.yml
c2cgeoportal/scaffolds/create/+package+.mk_tmpl
c2cgeoportal/scaffolds/create/CONST_print_url
c2cgeoportal/scaffolds/create/Dockerfile
c2cgeoportal/scaffolds/create/README.rst_tmpl
c2cgeoportal/scaffolds/create/alembic.ini.mako_tmpl
c2cgeoportal/scaffolds/create/alembic_static.ini.mako_tmpl
c2cgeoportal/scaffolds/create/development.ini.mako_tmpl
c2cgeoportal/scaffolds/create/docker-compose.yml.mako
c2cgeoportal/scaffolds/create/language_mapping
c2cgeoportal/scaffolds/create/lingua-client.cfg
c2cgeoportal/scaffolds/create/lingua-server.cfg
c2cgeoportal/scaffolds/create/package.json_tmpl
c2cgeoportal/scaffolds/create/production.ini.mako_tmpl
c2cgeoportal/scaffolds/create/project.yaml.mako_tmpl
c2cgeoportal/scaffolds/create/setup.cfg_tmpl
c2cgeoportal/scaffolds/create/setup.py_tmpl
c2cgeoportal/scaffolds/create/travis.mk_tmpl
c2cgeoportal/scaffolds/create/vars_+package+.yaml_tmpl
c2cgeoportal-2.2.10.dist-info/LICENSE.txt
c2cgeoportal-2.2.10.dist-info/METADATA
c2cgeoportal-2.2.10.dist-info/WHEEL
c2cgeoportal-2.2.10.dist-info/entry_points.txt
c2cgeoportal-2.2.10.dist-info/top_level.txt
c2cgeoportal-2.2.10.dist-info/RECORD
