Metadata-Version: 2.1
Name: c2cgeoportal
Version: 2.2.10
Summary: c2cgeoportal
Home-page: http://www.camptocamp.com/geospatial-solutions
Author: Camptocamp
Author-email: info@camptocamp.com
License: UNKNOWN
Keywords: web gis geoportail c2cgeoportal geocommune pyramid
Platform: UNKNOWN
Classifier: Programming Language :: Python
Classifier: Framework :: Pylons
Classifier: Topic :: Internet :: WWW/HTTP
Classifier: Topic :: Internet :: WWW/HTTP :: WSGI :: Application
Requires-Dist: pyramid (<=1.8.99)
Requires-Dist: pyramid-multiauth
Requires-Dist: pyramid-mako
Requires-Dist: pyramid-debugtoolbar
Requires-Dist: pyramid-chameleon
Requires-Dist: pyramid-formalchemy (>=0.4.3)
Requires-Dist: fa.jquery (>=0.9.5)
Requires-Dist: GeoFormAlchemy2 (>=2.0.dev2)
Requires-Dist: FormAlchemy
Requires-Dist: psycopg2
Requires-Dist: pycrypto
Requires-Dist: GeoAlchemy2
Requires-Dist: SQLAHelper
Requires-Dist: pyramid-tm
Requires-Dist: papyrus
Requires-Dist: ipcalc
Requires-Dist: httplib2
Requires-Dist: OWSLib (>=0.6.0)
Requires-Dist: dogpile.cache (>=0.6)
Requires-Dist: Paste
Requires-Dist: PasteDeploy
Requires-Dist: PasteScript
Requires-Dist: waitress
Requires-Dist: isodate
Requires-Dist: pyramid-closure
Requires-Dist: lingua
Requires-Dist: PyYAML
Requires-Dist: c2c.template (>=1.4.0)
Requires-Dist: defusedxml
Requires-Dist: dateutils
Requires-Dist: js.jquery (==1.7.1)
Requires-Dist: js.jqueryui (==1.8.24)
